toytable-0.0.46.dist-info/METADATA
toytable-0.0.46.dist-info/top_level.txt
toytable-0.0.46.dist-info/zip-safe
toytable-0.0.46.dist-info/WHEEL
toytable-0.0.46.dist-info/RECORD
toytable-0.0.46.dist-info/metadata.json
toytable-0.0.46.dist-info/DESCRIPTION.rst
toytable/columns.py
toytable/table.py
toytable/table_test_mixin.py
toytable/aggregation.py
toytable/index.py
toytable/exceptions.py
toytable/row.py
toytable/__init__.py
toytable/table_literal.py
toytable_tests/test_array_column.py
toytable_tests/test_project.py
toytable_tests/test_table.py
toytable_tests/test_table_literal.py
toytable_tests/test_repr.py
toytable_tests/test_expand.py
toytable_tests/test_row.py
toytable_tests/test_normalize.py
toytable_tests/test_index.py
toytable_tests/test_join.py
toytable_tests/test_slice.py
toytable_tests/test_restrict.py
toytable_tests/test_export.py
toytable_tests/test_aggregate.py
toytable_tests/test_rename.py
toytable_tests/__init__.py
toytable_tests/test_column.py
toytable_tests/test_table_test_mixin.py
toytable_tests/test_array_table.py
